<?xml version="1.0" ?>
<object name="portal_javascripts">

    <!-- disabled plone javascript for TCAA theme 
         Using jquery 1.7 in theme so disabling plone standard -->
    <javascript id="jquery.js"                                                                  expression="not:request/HTTP_X_THEME_ENABLED | nothing" /> 
    <javascript id="jquery-integration.js"                                                      expression="not:request/HTTP_X_THEME_ENABLED | nothing" /> 
    <javascript id="++resource++plone.app.jquerytools.js"                                       expression="not:request/HTTP_X_THEME_ENABLED | nothing" /> 
    <javascript id="++resource++plone.app.jquerytools.overlayhelpers.js"                        expression="not:request/HTTP_X_THEME_ENABLED | nothing" /> 
    <javascript id="++resource++plone.app.jquerytools.form.js"                                  expression="not:request/HTTP_X_THEME_ENABLED | nothing" /> 
    <javascript id="register_function.js"                                                       expression="not:request/HTTP_X_THEME_ENABLED | nothing" /> 
    <javascript id="livesearch.js"                                                              expression="not:request/HTTP_X_THEME_ENABLED | nothing" /> 
    <javascript id="dragdropreorder.js"                                                         expression="not:request/HTTP_X_THEME_ENABLED | nothing" /> 
    <javascript id="collapsiblesections.js"                                                     expression="not:request/HTTP_X_THEME_ENABLED | nothing" /> 
    <javascript id="form_tabbing.js"                                                            expression="not:request/HTTP_X_THEME_ENABLED | nothing" /> 
    <javascript id="popupforms.js"                                                              expression="not:request/HTTP_X_THEME_ENABLED | nothing" /> 
    <javascript id="input-label.js"                                                             expression="not:request/HTTP_X_THEME_ENABLED | nothing" /> 
    <javascript id="jquery.highlightsearchterms.js"                                             expression="not:request/HTTP_X_THEME_ENABLED | nothing" /> 
    <javascript id="first_input_focus.js"                                                       expression="not:request/HTTP_X_THEME_ENABLED | nothing" /> 
    <javascript id="accessibility.js"                                                           expression="not:request/HTTP_X_THEME_ENABLED | nothing" /> 
    <javascript id="styleswitcher.js"                                                           expression="not:request/HTTP_X_THEME_ENABLED | nothing" /> 
    <javascript id="toc.js"                                                                     expression="not:request/HTTP_X_THEME_ENABLED | nothing" /> 
    <javascript id="collapsibleformfields.js"                                                   expression="not:request/HTTP_X_THEME_ENABLED | nothing" /> 
    <javascript id="++resource++plone.app.discussion.javascripts/comments.js"                   expression="not:request/HTTP_X_THEME_ENABLED | nothing" /> 
    <javascript id="++resource++plone.formwidget.contenttree/contenttree.js"                    expression="not:request/HTTP_X_THEME_ENABLED | nothing" /> 
    <javascript id="++resource++plone.formwidget.autocomplete/jquery.autocomplete.min.js"       expression="not:request/HTTP_X_THEME_ENABLED | nothing" /> 
    <javascript id="++resource++plone.app.debugtoolbar/debugtoolbar.js"                         expression="not:request/HTTP_X_THEME_ENABLED | nothing" /> 

    <!-- TCAA theme javascript -->
    <javascript id="++theme++tcaa.theme/js/lib/jquery/1.7/jquery.min.js"                            expression="request/HTTP_X_THEME_ENABLED | nothing" 
                                                                                                    compression="none" insert-after="jquery.js"         />

    <javascript id="++theme++tcaa.theme/js/lib/jquery-hashchange/1.3/jquery.ba-hashchange.min.js"   expression="request/HTTP_X_THEME_ENABLED | nothing" />
    <javascript id="++theme++tcaa.theme/js/base.js"                                                 expression="request/HTTP_X_THEME_ENABLED | nothing" />
    
</object>
